noahs_google_drive_downloader/__init__.py
noahs_google_drive_downloader/downloader.py
noahs_google_drive_downloader-0.1.5.dist-info/METADATA
noahs_google_drive_downloader-0.1.5.dist-info/WHEEL
noahs_google_drive_downloader-0.1.5.dist-info/top_level.txt
noahs_google_drive_downloader-0.1.5.dist-info/RECORD
