Metadata-Version: 2.4
Name: noahs_google_drive_downloader
Version: 0.1.5
Summary: An simple extension of gdown that adds redundancy checks
Author-email: Noah Jones <jonesnoah45010@gmail.com>
License: MIT
Project-URL: Homepage, https://github.com/jonesnoah45010/google_drive_downloader
Requires-Python: >=3.9
Requires-Dist: gdown
